ngesh/__init__.py
ngesh/__main__.py
ngesh/common.py
ngesh/newick.py
ngesh/output.py
ngesh/random_tree.py
ngesh-1.2.1.dist-info/AUTHORS.md
ngesh-1.2.1.dist-info/LICENSE
ngesh-1.2.1.dist-info/METADATA
ngesh-1.2.1.dist-info/WHEEL
ngesh-1.2.1.dist-info/entry_points.txt
ngesh-1.2.1.dist-info/top_level.txt
ngesh-1.2.1.dist-info/RECORD
