Metadata-Version: 2.1
Name: ngesh
Version: 1.2.1
Summary: Simulate random phylogenetic trees
Home-page: https://github.com/tresoldi/ngesh
Author: Tiago Tresoldi
Author-email: tiago.tresoldi@lingfil.uu.se
License: MIT
Keywords: random phylogenetic tree,phylogenetics,simulation
Classifier: License :: OSI Approved :: MIT License
Classifier: Operating System :: OS Independent
Classifier: Programming Language :: Python :: 3
Classifier: Topic :: Software Development :: Libraries
Requires-Python: >=3.6
License-File: LICENSE
License-File: AUTHORS.md
Requires-Dist: ete3
Requires-Dist: numpy
Requires-Dist: six
Provides-Extra: dev
Requires-Dist: black ; extra == 'dev'
Requires-Dist: flake8 ; extra == 'dev'
Requires-Dist: twine ; extra == 'dev'
Requires-Dist: wheel ; extra == 'dev'
Provides-Extra: gfx
Requires-Dist: PyQt5 ; extra == 'gfx'
Provides-Extra: test
Requires-Dist: pytest ; extra == 'test'
